README.rst
setup.cfg
setup.py
parse_apache_configs/__init__.py
parse_apache_configs/parse_config.py
parse_apache_configs.egg-info/PKG-INFO
parse_apache_configs.egg-info/SOURCES.txt
parse_apache_configs.egg-info/dependency_links.txt
parse_apache_configs.egg-info/not-zip-safe
parse_apache_configs.egg-info/requires.txt
parse_apache_configs.egg-info/top_level.txt