Metadata-Version: 1.1
Name: parse-apache-configs
Version: 0.0.2
Summary: A python module to parse apache config files.
Home-page: http://github.com/alextricity25/parse_apache_configs
Author: Miguel Alex Cantu
Author-email: miguel.cantu@rackspace.com
License: UNKNOWN
Download-URL: https://github.com/alextricity25/parse_apache_configs/tarball/0.0.2
Platform: UNKNOWN
